correlation_integral.cpython-37m-x86_64-linux-gnu.so
correlation_integral.libs/libquadmath-96973f99.so.0.0.0
correlation_integral.libs/libgomp-a34b3233.so.1.0.0
correlation_integral.libs/libgfortran-040039e1.so.5.0.0
correlation_integral-0.0.5.dist-info/LICENSE
correlation_integral-0.0.5.dist-info/RECORD
correlation_integral-0.0.5.dist-info/top_level.txt
correlation_integral-0.0.5.dist-info/WHEEL
correlation_integral-0.0.5.dist-info/METADATA
