Metadata-Version: 2.1
Name: correlation-integral
Version: 0.0.5
Summary: Correlation Integral caluclations done fast with openmp
Home-page: https://github.com/v1kko/correlation_integral
Author: Victor Azizi
Author-email: victor@lipsum.eu
License: UNKNOWN
Platform: UNKNOWN
Classifier: Programming Language :: Python :: 3
Classifier: License :: OSI Approved :: GNU General Public License v3 (GPLv3)
Classifier: Operating System :: OS Independent
Requires-Python: >=3.6
License-File: LICENSE
Requires-Dist: numpy (>=1.18.0)
